livekit_utils/__init__.py
livekit_utils/utils.py
livekit_utils-0.18.0.dist-info/licenses/LICENSE
livekit_utils-0.18.0.dist-info/METADATA
livekit_utils-0.18.0.dist-info/WHEEL
livekit_utils-0.18.0.dist-info/top_level.txt
livekit_utils-0.18.0.dist-info/RECORD
