Metadata-Version: 2.4
Name: livekit_utils
Version: 0.18.0
Summary: livekit_utils
Author: livekit_utils
License: MIT
Classifier: Programming Language :: Python :: 3
Classifier: License :: OSI Approved :: MIT License
Classifier: Operating System :: OS Independent
Requires-Python: >=3.8
License-File: LICENSE
Dynamic: license-file
